{
  "rec_20260321_215421_567": {
    "status": "accepted",
    "updatedAt": "2026-07-02T01:42:32.468436Z",
    "auto": true
  },
  "rec_20260321_215816_313": {
    "status": "accepted",
    "updatedAt": "2026-07-02T01:42:32.468566Z",
    "auto": true
  },
  "rec_20260321_215816_892": {
    "status": "accepted",
    "updatedAt": "2026-07-02T01:42:32.468572Z",
    "auto": true
  },
  "rec_20260321_215816_115": {
    "status": "accepted",
    "updatedAt": "2026-07-02T01:42:32.468576Z",
    "auto": true
  },
  "rec_20260321_215816_378": {
    "status": "accepted",
    "updatedAt": "2026-07-02T01:42:32.468579Z",
    "auto": true
  },
  "rec_20260321_220007_674": {
    "status": "accepted",
    "updatedAt": "2026-07-02T01:42:32.468583Z",
    "auto": true
  },
  "rec_20260321_220007_124": {
    "status": "accepted",
    "updatedAt": "2026-07-02T01:42:32.468587Z",
    "auto": true
  },
  "rec_20260321_220007_219": {
    "status": "accepted",
    "updatedAt": "2026-07-02T01:42:32.468590Z",
    "auto": true
  },
  "rec_20260321_220007_505": {
    "status": "accepted",
    "updatedAt": "2026-07-02T01:42:32.468593Z",
    "auto": true
  },
  "rec_20260321_221410_746": {
    "status": "accepted",
    "updatedAt": "2026-07-02T01:42:32.468596Z",
    "auto": true
  },
  "rec_20260321_221410_154": {
    "status": "accepted",
    "updatedAt": "2026-07-02T01:42:32.468599Z",
    "auto": true
  },
  "rec_20260321_221410_393": {
    "status": "accepted",
    "updatedAt": "2026-07-02T01:42:32.468602Z",
    "auto": true
  },
  "rec_20260321_221410_817": {
    "status": "accepted",
    "updatedAt": "2026-07-02T01:42:32.468605Z",
    "auto": true
  },
  "rec_20260321_221501_594": {
    "status": "accepted",
    "updatedAt": "2026-07-02T01:42:32.468609Z",
    "auto": true
  },
  "rec_20260321_221501_112": {
    "status": "accepted",
    "updatedAt": "2026-07-02T01:42:32.468612Z",
    "auto": true
  },
  "rec_20260321_223032_719": {
    "status": "accepted",
    "updatedAt": "2026-07-02T01:42:32.468619Z",
    "auto": true
  },
  "rec_20260321_223032_329": {
    "status": "accepted",
    "updatedAt": "2026-07-02T01:42:32.468622Z",
    "auto": true
  },
  "rec_20260321_223315_361": {
    "status": "accepted",
    "updatedAt": "2026-07-02T01:42:32.468627Z",
    "auto": true
  },
  "rec_20260321_224501_654": {
    "status": "accepted",
    "updatedAt": "2026-07-02T01:42:32.468630Z",
    "auto": true
  },
  "rec_20260321_224501_554": {
    "status": "accepted",
    "updatedAt": "2026-07-02T01:42:32.468633Z",
    "auto": true
  },
  "rec_20260321_224501_429": {
    "status": "accepted",
    "updatedAt": "2026-07-02T01:42:32.468636Z",
    "auto": true
  },
  "rec_20260321_224501_845": {
    "status": "accepted",
    "updatedAt": "2026-07-02T01:42:32.468639Z",
    "auto": true
  },
  "rec_20260321_225133_572": {
    "status": "accepted",
    "updatedAt": "2026-07-02T01:42:32.468644Z",
    "auto": true
  },
  "rec_20260321_225133_618": {
    "status": "accepted",
    "updatedAt": "2026-07-02T01:42:32.468649Z",
    "auto": true
  },
  "rec_20260321_230001_488": {
    "status": "accepted",
    "updatedAt": "2026-07-02T01:42:32.468652Z",
    "auto": true
  },
  "rec_20260321_230001_444": {
    "status": "accepted",
    "updatedAt": "2026-07-02T01:42:32.468655Z",
    "auto": true
  },
  "rec_20260321_230001_859": {
    "status": "accepted",
    "updatedAt": "2026-07-02T01:42:32.468658Z",
    "auto": true
  },
  "rec_20260321_230001_521": {
    "status": "accepted",
    "updatedAt": "2026-07-02T01:42:32.468661Z",
    "auto": true
  },
  "rec_20260321_230844_158": {
    "status": "accepted",
    "updatedAt": "2026-07-02T01:42:32.468664Z",
    "auto": true
  },
  "rec_20260321_230844_964": {
    "status": "accepted",
    "updatedAt": "2026-07-02T01:42:32.468669Z",
    "auto": true
  },
  "rec_20260321_230844_204": {
    "status": "accepted",
    "updatedAt": "2026-07-02T01:42:32.468672Z",
    "auto": true
  },
  "rec_20260321_231507_106": {
    "status": "accepted",
    "updatedAt": "2026-07-02T01:42:32.468677Z",
    "auto": true
  },
  "rec_20260321_231507_587": {
    "status": "accepted",
    "updatedAt": "2026-07-02T01:42:32.468685Z",
    "auto": true
  },
  "rec_20260321_232509_911": {
    "status": "accepted",
    "updatedAt": "2026-07-02T01:42:32.468690Z",
    "auto": true
  },
  "rec_20260321_232509_543": {
    "status": "accepted",
    "updatedAt": "2026-07-02T01:42:32.468693Z",
    "auto": true
  },
  "rec_20260321_232509_410": {
    "status": "accepted",
    "updatedAt": "2026-07-02T01:42:32.468696Z",
    "auto": true
  },
  "rec_20260321_233001_610": {
    "status": "accepted",
    "updatedAt": "2026-07-02T01:42:32.468699Z",
    "auto": true
  },
  "rec_20260321_233001_255": {
    "status": "accepted",
    "updatedAt": "2026-07-02T01:42:32.468702Z",
    "auto": true
  },
  "rec_20260321_233001_300": {
    "status": "accepted",
    "updatedAt": "2026-07-02T01:42:32.468705Z",
    "auto": true
  },
  "rec_20260321_233001_280": {
    "status": "accepted",
    "updatedAt": "2026-07-02T01:42:32.468708Z",
    "auto": true
  },
  "rec_20260321_234108_844": {
    "status": "accepted",
    "updatedAt": "2026-07-02T01:42:32.468713Z",
    "auto": true
  },
  "rec_20260321_234737_707": {
    "status": "accepted",
    "updatedAt": "2026-07-02T01:42:32.468716Z",
    "auto": true
  },
  "rec_20260322_000002_278": {
    "status": "accepted",
    "updatedAt": "2026-07-02T01:42:32.468720Z",
    "auto": true
  },
  "rec_20260322_000002_301": {
    "status": "accepted",
    "updatedAt": "2026-07-02T01:42:32.468724Z",
    "auto": true
  },
  "rec_20260322_001501_779": {
    "status": "accepted",
    "updatedAt": "2026-07-02T01:42:32.468728Z",
    "auto": true
  },
  "rec_20260322_001501_819": {
    "status": "accepted",
    "updatedAt": "2026-07-02T01:42:32.468731Z",
    "auto": true
  },
  "rec_20260322_001501_532": {
    "status": "accepted",
    "updatedAt": "2026-07-02T01:42:32.468734Z",
    "auto": true
  },
  "rec_20260322_003001_818": {
    "status": "accepted",
    "updatedAt": "2026-07-02T01:42:32.468739Z",
    "auto": true
  },
  "rec_20260322_003001_796": {
    "status": "accepted",
    "updatedAt": "2026-07-02T01:42:32.468742Z",
    "auto": true
  },
  "rec_20260322_003001_351": {
    "status": "accepted",
    "updatedAt": "2026-07-02T01:42:32.468745Z",
    "auto": true
  },
  "rec_20260322_004500_947": {
    "status": "accepted",
    "updatedAt": "2026-07-02T01:42:32.468748Z",
    "auto": true
  },
  "rec_20260322_004500_227": {
    "status": "accepted",
    "updatedAt": "2026-07-02T01:42:32.468751Z",
    "auto": true
  },
  "rec_20260322_004500_502": {
    "status": "accepted",
    "updatedAt": "2026-07-02T01:42:32.468754Z",
    "auto": true
  },
  "rec_20260322_004500_646": {
    "status": "accepted",
    "updatedAt": "2026-07-02T01:42:32.468757Z",
    "auto": true
  },
  "rec_20260322_010002_682": {
    "status": "accepted",
    "updatedAt": "2026-07-02T01:42:32.468765Z",
    "auto": true
  },
  "rec_20260322_010002_158": {
    "status": "accepted",
    "updatedAt": "2026-07-02T01:42:32.468768Z",
    "auto": true
  },
  "rec_20260322_010002_425": {
    "status": "accepted",
    "updatedAt": "2026-07-02T01:42:32.468771Z",
    "auto": true
  },
  "rec_20260322_010002_861": {
    "status": "accepted",
    "updatedAt": "2026-07-02T01:42:32.468774Z",
    "auto": true
  },
  "rec_20260322_010002_528": {
    "status": "accepted",
    "updatedAt": "2026-07-02T01:42:32.468777Z",
    "auto": true
  },
  "rec_20260322_011318_790": {
    "status": "accepted",
    "updatedAt": "2026-07-02T01:42:32.468782Z",
    "auto": true
  },
  "rec_20260322_011318_324": {
    "status": "accepted",
    "updatedAt": "2026-07-02T01:42:32.468786Z",
    "auto": true
  },
  "rec_20260322_011501_912": {
    "status": "accepted",
    "updatedAt": "2026-07-02T01:42:32.468793Z",
    "auto": true
  },
  "rec_20260322_011501_923": {
    "status": "accepted",
    "updatedAt": "2026-07-02T01:42:32.468796Z",
    "auto": true
  },
  "rec_20260322_011501_843": {
    "status": "accepted",
    "updatedAt": "2026-07-02T01:42:32.468799Z",
    "auto": true
  },
  "rec_20260322_011501_623": {
    "status": "accepted",
    "updatedAt": "2026-07-02T01:42:32.468802Z",
    "auto": true
  },
  "rec_20260322_013000_944": {
    "status": "accepted",
    "updatedAt": "2026-07-02T01:42:32.468805Z",
    "auto": true
  },
  "rec_20260322_013000_885": {
    "status": "accepted",
    "updatedAt": "2026-07-02T01:42:32.468808Z",
    "auto": true
  },
  "rec_20260322_013000_930": {
    "status": "accepted",
    "updatedAt": "2026-07-02T01:42:32.468811Z",
    "auto": true
  },
  "rec_20260322_013000_585": {
    "status": "accepted",
    "updatedAt": "2026-07-02T01:42:32.468814Z",
    "auto": true
  },
  "rec_20260322_014500_621": {
    "status": "accepted",
    "updatedAt": "2026-07-02T01:42:32.468818Z",
    "auto": true
  },
  "rec_20260322_014500_913": {
    "status": "accepted",
    "updatedAt": "2026-07-02T01:42:32.468821Z",
    "auto": true
  },
  "rec_20260322_014500_393": {
    "status": "accepted",
    "updatedAt": "2026-07-02T01:42:32.468824Z",
    "auto": true
  },
  "rec_20260322_014500_967": {
    "status": "accepted",
    "updatedAt": "2026-07-02T01:42:32.468827Z",
    "auto": true
  },
  "rec_20260702_001501_911": {
    "status": "accepted",
    "updatedAt": "2026-07-02T01:42:32.468832Z",
    "auto": true
  },
  "rec_20260702_001501_411": {
    "status": "accepted",
    "updatedAt": "2026-07-02T01:42:32.468835Z",
    "auto": true
  },
  "rec_20260702_001501_778": {
    "status": "accepted",
    "updatedAt": "2026-07-02T01:42:32.468838Z",
    "auto": true
  },
  "rec_20260702_001501_805": {
    "status": "accepted",
    "updatedAt": "2026-07-02T01:42:32.468841Z",
    "auto": true
  },
  "rec_20260702_001501_967": {
    "status": "accepted",
    "updatedAt": "2026-07-02T01:42:32.468844Z",
    "auto": true
  },
  "rec_20260702_001501_539": {
    "status": "accepted",
    "updatedAt": "2026-07-02T01:42:32.468847Z",
    "auto": true
  },
  "rec_20260702_001501_589": {
    "status": "accepted",
    "updatedAt": "2026-07-02T01:42:32.468850Z",
    "auto": true
  },
  "rec_20260702_001501_888": {
    "status": "accepted",
    "updatedAt": "2026-07-02T01:42:32.468853Z",
    "auto": true
  },
  "rec_20260702_001501_787": {
    "status": "accepted",
    "updatedAt": "2026-07-02T01:42:32.468856Z",
    "auto": true
  },
  "rec_20260702_003001_412": {
    "status": "accepted",
    "updatedAt": "2026-07-02T01:42:32.468861Z",
    "auto": true
  },
  "rec_20260702_003001_224": {
    "status": "accepted",
    "updatedAt": "2026-07-02T01:42:32.468864Z",
    "auto": true
  },
  "rec_20260702_003001_624": {
    "status": "accepted",
    "updatedAt": "2026-07-02T01:42:32.468867Z",
    "auto": true
  },
  "rec_20260702_003001_713": {
    "status": "accepted",
    "updatedAt": "2026-07-02T01:42:32.468870Z",
    "auto": true
  },
  "rec_20260702_003001_180": {
    "status": "accepted",
    "updatedAt": "2026-07-02T01:42:32.468873Z",
    "auto": true
  },
  "rec_20260702_003001_160": {
    "status": "accepted",
    "updatedAt": "2026-07-02T01:42:32.468876Z",
    "auto": true
  },
  "rec_20260702_004500_419": {
    "status": "accepted",
    "updatedAt": "2026-07-02T01:42:32.468879Z",
    "auto": true
  },
  "rec_20260702_004500_592": {
    "status": "accepted",
    "updatedAt": "2026-07-02T01:42:32.468882Z",
    "auto": true
  },
  "rec_20260702_004500_810": {
    "status": "accepted",
    "updatedAt": "2026-07-02T01:42:32.468885Z",
    "auto": true
  },
  "rec_20260702_004500_362": {
    "status": "accepted",
    "updatedAt": "2026-07-02T01:42:32.468888Z",
    "auto": true
  },
  "rec_20260702_004500_781": {
    "status": "accepted",
    "updatedAt": "2026-07-02T01:42:32.468893Z",
    "auto": true
  },
  "rec_20260702_004500_785": {
    "status": "accepted",
    "updatedAt": "2026-07-02T01:42:32.468896Z",
    "auto": true
  },
  "rec_20260702_010001_952": {
    "status": "accepted",
    "updatedAt": "2026-07-02T01:42:32.468901Z",
    "auto": true
  },
  "rec_20260702_010001_850": {
    "status": "accepted",
    "updatedAt": "2026-07-02T01:42:32.468905Z",
    "auto": true
  },
  "rec_20260702_010001_111": {
    "status": "accepted",
    "updatedAt": "2026-07-02T01:42:32.468908Z",
    "auto": true
  },
  "rec_20260702_010001_539": {
    "status": "accepted",
    "updatedAt": "2026-07-02T01:42:32.468911Z",
    "auto": true
  },
  "rec_20260702_010001_305": {
    "status": "accepted",
    "updatedAt": "2026-07-02T01:42:32.468914Z",
    "auto": true
  },
  "rec_20260702_010001_586": {
    "status": "accepted",
    "updatedAt": "2026-07-02T01:42:32.468917Z",
    "auto": true
  },
  "rec_20260702_010001_130": {
    "status": "accepted",
    "updatedAt": "2026-07-02T01:42:32.468920Z",
    "auto": true
  },
  "rec_20260702_010001_616": {
    "status": "accepted",
    "updatedAt": "2026-07-02T01:42:32.468923Z",
    "auto": true
  },
  "rec_20260702_010001_260": {
    "status": "accepted",
    "updatedAt": "2026-07-02T01:42:32.468926Z",
    "auto": true
  },
  "rec_20260702_011501_863": {
    "status": "accepted",
    "updatedAt": "2026-07-02T01:42:32.468930Z",
    "auto": true
  },
  "rec_20260702_011501_814": {
    "status": "accepted",
    "updatedAt": "2026-07-02T01:42:32.468933Z",
    "auto": true
  },
  "rec_20260702_011501_441": {
    "status": "accepted",
    "updatedAt": "2026-07-02T01:42:32.468936Z",
    "auto": true
  },
  "rec_20260702_011501_887": {
    "status": "accepted",
    "updatedAt": "2026-07-02T01:42:32.468939Z",
    "auto": true
  },
  "rec_20260702_011501_289": {
    "status": "accepted",
    "updatedAt": "2026-07-02T01:42:32.468946Z",
    "auto": true
  },
  "rec_20260702_011501_997": {
    "status": "accepted",
    "updatedAt": "2026-07-02T01:42:32.468949Z",
    "auto": true
  },
  "rec_20260702_011501_574": {
    "status": "accepted",
    "updatedAt": "2026-07-02T01:42:32.468952Z",
    "auto": true
  },
  "rec_20260702_013001_685": {
    "status": "accepted",
    "updatedAt": "2026-07-02T01:42:32.468955Z",
    "auto": true
  },
  "rec_20260702_013001_842": {
    "status": "accepted",
    "updatedAt": "2026-07-02T01:42:32.468958Z",
    "auto": true
  },
  "rec_20260702_013001_542": {
    "status": "accepted",
    "updatedAt": "2026-07-02T01:42:32.468961Z",
    "auto": true
  },
  "rec_20260702_013001_528": {
    "status": "accepted",
    "updatedAt": "2026-07-02T01:42:32.468964Z",
    "auto": true
  },
  "rec_20260702_013001_648": {
    "status": "accepted",
    "updatedAt": "2026-07-02T01:42:32.468967Z",
    "auto": true
  },
  "rec_20260702_013001_225": {
    "status": "accepted",
    "updatedAt": "2026-07-02T01:42:32.468970Z",
    "auto": true
  },
  "rec_20260702_013001_791": {
    "status": "accepted",
    "updatedAt": "2026-07-02T01:42:32.468977Z",
    "auto": true
  },
  "rec_20260702_013001_251": {
    "status": "accepted",
    "updatedAt": "2026-07-02T01:42:32.468980Z",
    "auto": true
  },
  "rec_20260702_014229_674": {
    "status": "accepted",
    "updatedAt": "2026-07-02T01:42:32.468983Z",
    "auto": true
  },
  "rec_20260702_014229_414": {
    "status": "accepted",
    "updatedAt": "2026-07-02T01:42:32.468986Z",
    "auto": true
  },
  "rec_20260702_014229_875": {
    "status": "accepted",
    "updatedAt": "2026-07-02T01:42:32.468989Z",
    "auto": true
  },
  "rec_20260702_014229_437": {
    "status": "accepted",
    "updatedAt": "2026-07-02T01:42:32.468992Z",
    "auto": true
  },
  "rec_20260702_014229_563": {
    "status": "accepted",
    "updatedAt": "2026-07-02T01:42:32.468995Z",
    "auto": true
  },
  "rec_20260702_014229_108": {
    "status": "accepted",
    "updatedAt": "2026-07-02T01:42:32.468998Z",
    "auto": true
  },
  "rec_20260702_014229_229": {
    "status": "accepted",
    "updatedAt": "2026-07-02T01:42:32.469000Z",
    "auto": true
  },
  "rec_20260702_014300_977": {
    "status": "accepted",
    "updatedAt": "2026-07-02T01:43:32.492Z"
  },
  "rec_20260702_014300_114": {
    "status": "accepted",
    "updatedAt": "2026-07-02T01:43:40.468Z"
  },
  "rec_20260702_014300_888": {
    "status": "accepted",
    "updatedAt": "2026-07-02T01:43:46.297Z"
  },
  "rec_20260702_014300_422": {
    "status": "accepted",
    "updatedAt": "2026-07-02T01:43:53.852Z"
  },
  "rec_20260702_014753_901": {
    "status": "accepted",
    "updatedAt": "2026-07-02T01:50:29.500Z"
  },
  "rec_20260702_014753_755": {
    "status": "accepted",
    "updatedAt": "2026-07-02T01:50:30.569Z"
  },
  "rec_20260702_014753_252": {
    "status": "rejected",
    "updatedAt": "2026-07-02T01:50:34.871Z"
  },
  "rec_20260702_014753_301": {
    "status": "rejected",
    "updatedAt": "2026-07-02T01:50:40.609Z"
  },
  "rec_20260702_014753_531": {
    "status": "accepted",
    "updatedAt": "2026-07-02T01:50:47.630Z"
  },
  "rec_20260702_014753_303": {
    "status": "rejected",
    "updatedAt": "2026-07-02T01:50:51.036Z"
  },
  "rec_20260702_014753_579": {
    "status": "rejected",
    "updatedAt": "2026-07-02T01:50:53.392Z"
  },
  "rec_20260702_015425_700": {
    "status": "rejected",
    "updatedAt": "2026-07-02T01:54:37.679Z"
  },
  "rec_20260702_015425_673": {
    "status": "rejected",
    "updatedAt": "2026-07-02T01:54:40.213Z"
  },
  "rec_20260702_020801_335": {
    "status": "accepted",
    "updatedAt": "2026-07-02T02:12:22.737Z"
  },
  "rec_20260702_020801_913": {
    "status": "rejected",
    "updatedAt": "2026-07-02T02:12:28.889Z"
  },
  "rec_20260702_014300_551": {
    "status": "accepted",
    "updatedAt": "2026-07-02T02:52:58.687191Z",
    "auto": true
  },
  "rec_20260702_014300_820": {
    "status": "accepted",
    "updatedAt": "2026-07-02T02:52:58.687321Z",
    "auto": true
  },
  "rec_20260702_014501_371": {
    "status": "accepted",
    "updatedAt": "2026-07-02T02:52:58.687337Z",
    "auto": true
  },
  "rec_20260702_014501_298": {
    "status": "accepted",
    "updatedAt": "2026-07-02T02:52:58.687341Z",
    "auto": true
  },
  "rec_20260702_014501_558": {
    "status": "accepted",
    "updatedAt": "2026-07-02T02:52:58.687344Z",
    "auto": true
  },
  "rec_20260702_014501_643": {
    "status": "accepted",
    "updatedAt": "2026-07-02T02:52:58.687348Z",
    "auto": true
  },
  "rec_20260702_014501_704": {
    "status": "accepted",
    "updatedAt": "2026-07-02T02:52:58.687351Z",
    "auto": true
  },
  "rec_20260702_014501_444": {
    "status": "accepted",
    "updatedAt": "2026-07-02T02:52:58.687354Z",
    "auto": true
  },
  "rec_20260702_014501_594": {
    "status": "accepted",
    "updatedAt": "2026-07-02T02:52:58.687358Z",
    "auto": true
  },
  "rec_20260702_014501_515": {
    "status": "accepted",
    "updatedAt": "2026-07-02T02:52:58.687361Z",
    "auto": true
  },
  "rec_20260702_015425_907": {
    "status": "accepted",
    "updatedAt": "2026-07-02T02:52:58.687378Z",
    "auto": true
  },
  "rec_20260702_015425_425": {
    "status": "accepted",
    "updatedAt": "2026-07-02T02:52:58.687383Z",
    "auto": true
  },
  "rec_20260702_015425_534": {
    "status": "accepted",
    "updatedAt": "2026-07-02T02:52:58.687389Z",
    "auto": true
  },
  "rec_20260702_015425_368": {
    "status": "accepted",
    "updatedAt": "2026-07-02T02:52:58.687392Z",
    "auto": true
  },
  "rec_20260702_015425_621": {
    "status": "accepted",
    "updatedAt": "2026-07-02T02:52:58.687395Z",
    "auto": true
  },
  "rec_20260702_015425_525": {
    "status": "accepted",
    "updatedAt": "2026-07-02T02:52:58.687398Z",
    "auto": true
  },
  "rec_20260702_020000_684": {
    "status": "accepted",
    "updatedAt": "2026-07-02T02:52:58.687409Z",
    "auto": true
  },
  "rec_20260702_020000_913": {
    "status": "accepted",
    "updatedAt": "2026-07-02T02:52:58.687414Z",
    "auto": true
  },
  "rec_20260702_020000_217": {
    "status": "accepted",
    "updatedAt": "2026-07-02T02:52:58.687417Z",
    "auto": true
  },
  "rec_20260702_020000_570": {
    "status": "accepted",
    "updatedAt": "2026-07-02T02:52:58.687421Z",
    "auto": true
  },
  "rec_20260702_020000_790": {
    "status": "accepted",
    "updatedAt": "2026-07-02T02:52:58.687424Z",
    "auto": true
  },
  "rec_20260702_020043_827": {
    "status": "accepted",
    "updatedAt": "2026-07-02T02:52:58.687427Z",
    "auto": true
  },
  "rec_20260702_020043_214": {
    "status": "accepted",
    "updatedAt": "2026-07-02T02:52:58.687430Z",
    "auto": true
  },
  "rec_20260702_020043_895": {
    "status": "accepted",
    "updatedAt": "2026-07-02T02:52:58.687434Z",
    "auto": true
  },
  "rec_20260702_020043_755": {
    "status": "accepted",
    "updatedAt": "2026-07-02T02:52:58.687439Z",
    "auto": true
  },
  "rec_20260702_020043_201": {
    "status": "accepted",
    "updatedAt": "2026-07-02T02:52:58.687442Z",
    "auto": true
  },
  "rec_20260702_020043_365": {
    "status": "accepted",
    "updatedAt": "2026-07-02T02:52:58.687446Z",
    "auto": true
  },
  "rec_20260702_020043_372": {
    "status": "accepted",
    "updatedAt": "2026-07-02T02:52:58.687449Z",
    "auto": true
  },
  "rec_20260702_020044_551": {
    "status": "accepted",
    "updatedAt": "2026-07-02T02:52:58.687454Z",
    "auto": true
  },
  "rec_20260702_020044_142": {
    "status": "accepted",
    "updatedAt": "2026-07-02T02:52:58.687457Z",
    "auto": true
  },
  "rec_20260702_020044_262": {
    "status": "accepted",
    "updatedAt": "2026-07-02T02:52:58.687462Z",
    "auto": true
  },
  "rec_20260702_020044_521": {
    "status": "accepted",
    "updatedAt": "2026-07-02T02:52:58.687467Z",
    "auto": true
  },
  "rec_20260702_020044_769": {
    "status": "accepted",
    "updatedAt": "2026-07-02T02:52:58.687470Z",
    "auto": true
  },
  "rec_20260702_020044_923": {
    "status": "accepted",
    "updatedAt": "2026-07-02T02:52:58.687475Z",
    "auto": true
  },
  "rec_20260702_020750_543": {
    "status": "accepted",
    "updatedAt": "2026-07-02T02:52:58.687480Z",
    "auto": true
  },
  "rec_20260702_020750_772": {
    "status": "accepted",
    "updatedAt": "2026-07-02T02:52:58.687485Z",
    "auto": true
  },
  "rec_20260702_020750_529": {
    "status": "accepted",
    "updatedAt": "2026-07-02T02:52:58.687488Z",
    "auto": true
  },
  "rec_20260702_020750_947": {
    "status": "accepted",
    "updatedAt": "2026-07-02T02:52:58.687491Z",
    "auto": true
  },
  "rec_20260702_020750_163": {
    "status": "accepted",
    "updatedAt": "2026-07-02T02:52:58.687494Z",
    "auto": true
  },
  "rec_20260702_020750_479": {
    "status": "accepted",
    "updatedAt": "2026-07-02T02:52:58.687497Z",
    "auto": true
  },
  "rec_20260702_020801_708": {
    "status": "accepted",
    "updatedAt": "2026-07-02T02:52:58.687503Z",
    "auto": true
  },
  "rec_20260702_020801_954": {
    "status": "accepted",
    "updatedAt": "2026-07-02T02:52:58.687507Z",
    "auto": true
  },
  "rec_20260702_020801_277": {
    "status": "accepted",
    "updatedAt": "2026-07-02T02:52:58.687512Z",
    "auto": true
  },
  "rec_20260702_020801_359": {
    "status": "accepted",
    "updatedAt": "2026-07-02T02:52:58.687516Z",
    "auto": true
  },
  "rec_20260702_020801_798": {
    "status": "accepted",
    "updatedAt": "2026-07-02T02:52:58.687519Z",
    "auto": true
  },
  "rec_20260702_020801_442": {
    "status": "accepted",
    "updatedAt": "2026-07-02T02:52:58.687522Z",
    "auto": true
  },
  "rec_20260702_020801_400": {
    "status": "accepted",
    "updatedAt": "2026-07-02T02:52:58.687525Z",
    "auto": true
  },
  "rec_20260702_021315_332": {
    "status": "accepted",
    "updatedAt": "2026-07-02T02:52:58.687534Z",
    "auto": true
  },
  "rec_20260702_021315_209": {
    "status": "accepted",
    "updatedAt": "2026-07-02T02:52:58.687537Z",
    "auto": true
  },
  "rec_20260702_021315_830": {
    "status": "accepted",
    "updatedAt": "2026-07-02T02:52:58.687540Z",
    "auto": true
  },
  "rec_20260702_021315_529": {
    "status": "accepted",
    "updatedAt": "2026-07-02T02:52:58.687543Z",
    "auto": true
  },
  "rec_20260702_021315_171": {
    "status": "accepted",
    "updatedAt": "2026-07-02T02:52:58.687548Z",
    "auto": true
  },
  "rec_20260702_021315_457": {
    "status": "accepted",
    "updatedAt": "2026-07-02T02:52:58.687551Z",
    "auto": true
  },
  "rec_20260702_021315_710": {
    "status": "accepted",
    "updatedAt": "2026-07-02T02:52:58.687554Z",
    "auto": true
  },
  "rec_20260702_021501_622": {
    "status": "accepted",
    "updatedAt": "2026-07-02T02:52:58.687557Z",
    "auto": true
  },
  "rec_20260702_021501_581": {
    "status": "accepted",
    "updatedAt": "2026-07-02T02:52:58.687560Z",
    "auto": true
  },
  "rec_20260702_021501_104": {
    "status": "accepted",
    "updatedAt": "2026-07-02T02:52:58.687564Z",
    "auto": true
  },
  "rec_20260702_021501_716": {
    "status": "accepted",
    "updatedAt": "2026-07-02T02:52:58.687567Z",
    "auto": true
  },
  "rec_20260702_021501_924": {
    "status": "accepted",
    "updatedAt": "2026-07-02T02:52:58.687570Z",
    "auto": true
  },
  "rec_20260702_021501_942": {
    "status": "accepted",
    "updatedAt": "2026-07-02T02:52:58.687573Z",
    "auto": true
  },
  "rec_20260702_021501_117": {
    "status": "accepted",
    "updatedAt": "2026-07-02T02:52:58.687576Z",
    "auto": true
  },
  "rec_20260702_021501_438": {
    "status": "accepted",
    "updatedAt": "2026-07-02T02:52:58.687579Z",
    "auto": true
  },
  "rec_20260702_021501_667": {
    "status": "accepted",
    "updatedAt": "2026-07-02T02:52:58.687584Z",
    "auto": true
  },
  "rec_20260702_021841_807": {
    "status": "accepted",
    "updatedAt": "2026-07-02T02:52:58.687587Z",
    "auto": true
  },
  "rec_20260702_021841_605": {
    "status": "accepted",
    "updatedAt": "2026-07-02T02:52:58.687590Z",
    "auto": true
  },
  "rec_20260702_021841_296": {
    "status": "accepted",
    "updatedAt": "2026-07-02T02:52:58.687593Z",
    "auto": true
  },
  "rec_20260702_021841_404": {
    "status": "accepted",
    "updatedAt": "2026-07-02T02:52:58.687599Z",
    "auto": true
  },
  "rec_20260702_021841_177": {
    "status": "accepted",
    "updatedAt": "2026-07-02T02:52:58.687608Z",
    "auto": true
  },
  "2b804071-078b-460a-b740-a2da1780c197": {
    "status": "accepted",
    "updatedAt": "2026-07-02T02:52:58.687611Z",
    "auto": true
  },
  "e41a9abb-69c3-49f7-a091-5588f7f5965d": {
    "status": "accepted",
    "updatedAt": "2026-07-02T02:52:58.687614Z",
    "auto": true
  },
  "9e1ad694-5680-40af-9d01-415e09a5ab2b": {
    "status": "accepted",
    "updatedAt": "2026-07-02T02:52:58.687617Z",
    "auto": true
  },
  "rec_20260702_022459_627": {
    "status": "accepted",
    "updatedAt": "2026-07-02T02:52:58.687623Z",
    "auto": true
  },
  "rec_20260702_022459_783": {
    "status": "accepted",
    "updatedAt": "2026-07-02T02:52:58.687628Z",
    "auto": true
  },
  "rec_20260702_022459_326": {
    "status": "accepted",
    "updatedAt": "2026-07-02T02:52:58.687631Z",
    "auto": true
  },
  "rec_20260702_022459_200": {
    "status": "accepted",
    "updatedAt": "2026-07-02T02:52:58.687634Z",
    "auto": true
  },
  "rec_20260702_022459_685": {
    "status": "accepted",
    "updatedAt": "2026-07-02T02:52:58.687641Z",
    "auto": true
  },
  "rec_20260702_022459_347": {
    "status": "accepted",
    "updatedAt": "2026-07-02T02:52:58.687644Z",
    "auto": true
  },
  "rec_20260702_023001_890": {
    "status": "accepted",
    "updatedAt": "2026-07-02T02:52:58.687649Z",
    "auto": true
  },
  "rec_20260702_023001_251": {
    "status": "accepted",
    "updatedAt": "2026-07-02T02:52:58.687652Z",
    "auto": true
  },
  "rec_20260702_023001_673": {
    "status": "accepted",
    "updatedAt": "2026-07-02T02:52:58.687655Z",
    "auto": true
  },
  "rec_20260702_023001_456": {
    "status": "accepted",
    "updatedAt": "2026-07-02T02:52:58.687658Z",
    "auto": true
  },
  "rec_20260702_023001_788": {
    "status": "accepted",
    "updatedAt": "2026-07-02T02:52:58.687661Z",
    "auto": true
  },
  "rec_20260702_023001_116": {
    "status": "accepted",
    "updatedAt": "2026-07-02T02:52:58.687664Z",
    "auto": true
  },
  "rec_20260702_023001_935": {
    "status": "accepted",
    "updatedAt": "2026-07-02T02:52:58.687668Z",
    "auto": true
  },
  "rec_20260702_023001_843": {
    "status": "accepted",
    "updatedAt": "2026-07-02T02:52:58.687671Z",
    "auto": true
  },
  "rec_20260702_023104_196": {
    "status": "accepted",
    "updatedAt": "2026-07-02T02:52:58.687676Z",
    "auto": true
  },
  "rec_20260702_023104_471": {
    "status": "accepted",
    "updatedAt": "2026-07-02T02:52:58.687679Z",
    "auto": true
  },
  "rec_20260702_023104_159": {
    "status": "accepted",
    "updatedAt": "2026-07-02T02:52:58.687682Z",
    "auto": true
  },
  "rec_20260702_023104_102": {
    "status": "accepted",
    "updatedAt": "2026-07-02T02:52:58.687687Z",
    "auto": true
  },
  "rec_20260702_023104_900": {
    "status": "accepted",
    "updatedAt": "2026-07-02T02:52:58.687690Z",
    "auto": true
  },
  "rec_20260702_023104_943": {
    "status": "accepted",
    "updatedAt": "2026-07-02T02:52:58.687693Z",
    "auto": true
  },
  "rec_20260702_023104_151": {
    "status": "accepted",
    "updatedAt": "2026-07-02T02:52:58.687696Z",
    "auto": true
  },
  "rec_20260702_023627_320": {
    "status": "accepted",
    "updatedAt": "2026-07-02T02:52:58.687703Z",
    "auto": true
  },
  "rec_20260702_023627_324": {
    "status": "accepted",
    "updatedAt": "2026-07-02T02:52:58.687708Z",
    "auto": true
  },
  "rec_20260702_023627_308": {
    "status": "accepted",
    "updatedAt": "2026-07-02T02:52:58.687711Z",
    "auto": true
  },
  "rec_20260702_023627_776": {
    "status": "accepted",
    "updatedAt": "2026-07-02T02:52:58.687714Z",
    "auto": true
  },
  "rec_20260702_024150_979": {
    "status": "accepted",
    "updatedAt": "2026-07-02T02:52:58.687717Z",
    "auto": true
  },
  "rec_20260702_024150_306": {
    "status": "accepted",
    "updatedAt": "2026-07-02T02:52:58.687720Z",
    "auto": true
  },
  "rec_20260702_024150_602": {
    "status": "accepted",
    "updatedAt": "2026-07-02T02:52:58.687723Z",
    "auto": true
  },
  "rec_20260702_024150_147": {
    "status": "accepted",
    "updatedAt": "2026-07-02T02:52:58.687726Z",
    "auto": true
  },
  "rec_20260702_024150_494": {
    "status": "accepted",
    "updatedAt": "2026-07-02T02:52:58.687730Z",
    "auto": true
  },
  "rec_20260702_024150_283": {
    "status": "accepted",
    "updatedAt": "2026-07-02T02:52:58.687733Z",
    "auto": true
  },
  "rec_20260702_024150_352": {
    "status": "accepted",
    "updatedAt": "2026-07-02T02:52:58.687740Z",
    "auto": true
  },
  "rec_20260702_024501_653": {
    "status": "accepted",
    "updatedAt": "2026-07-02T02:52:58.687745Z",
    "auto": true
  },
  "rec_20260702_024501_736": {
    "status": "accepted",
    "updatedAt": "2026-07-02T02:52:58.687748Z",
    "auto": true
  },
  "rec_20260702_024501_437": {
    "status": "accepted",
    "updatedAt": "2026-07-02T02:52:58.687751Z",
    "auto": true
  },
  "rec_20260702_024501_667": {
    "status": "accepted",
    "updatedAt": "2026-07-02T02:52:58.687754Z",
    "auto": true
  },
  "rec_20260702_024501_967": {
    "status": "accepted",
    "updatedAt": "2026-07-02T02:52:58.687757Z",
    "auto": true
  },
  "rec_20260702_024501_598": {
    "status": "accepted",
    "updatedAt": "2026-07-02T02:52:58.687760Z",
    "auto": true
  },
  "rec_20260702_024501_236": {
    "status": "accepted",
    "updatedAt": "2026-07-02T02:52:58.687765Z",
    "auto": true
  },
  "rec_20260702_024501_687": {
    "status": "accepted",
    "updatedAt": "2026-07-02T02:52:58.687768Z",
    "auto": true
  },
  "rec_20260702_024727_941": {
    "status": "accepted",
    "updatedAt": "2026-07-02T02:52:58.687772Z",
    "auto": true
  },
  "rec_20260702_024727_167": {
    "status": "accepted",
    "updatedAt": "2026-07-02T02:52:58.687775Z",
    "auto": true
  },
  "rec_20260702_024727_236": {
    "status": "accepted",
    "updatedAt": "2026-07-02T02:52:58.687778Z",
    "auto": true
  },
  "rec_20260702_024727_836": {
    "status": "accepted",
    "updatedAt": "2026-07-02T02:52:58.687781Z",
    "auto": true
  },
  "rec_20260702_024727_100": {
    "status": "accepted",
    "updatedAt": "2026-07-02T02:52:58.687784Z",
    "auto": true
  },
  "rec_20260702_024727_226": {
    "status": "accepted",
    "updatedAt": "2026-07-02T02:52:58.687787Z",
    "auto": true
  },
  "26f36a3b-65d2-4711-8ae9-67a85f1a35de": {
    "status": "accepted",
    "updatedAt": "2026-07-02T02:52:58.687792Z",
    "auto": true
  },
  "54bdd1b5-7824-433a-8cdf-ec7f6abf78f1": {
    "status": "accepted",
    "updatedAt": "2026-07-02T02:52:58.687795Z",
    "auto": true
  },
  "a62243f8-a2f4-4598-8929-945be0560dde": {
    "status": "accepted",
    "updatedAt": "2026-07-02T02:52:58.687797Z",
    "auto": true
  },
  "092fb15e-a801-4d11-b228-cf959304cd07": {
    "status": "accepted",
    "updatedAt": "2026-07-02T02:52:58.687800Z",
    "auto": true
  },
  "c285ac9d-5f08-4dfa-9c7c-56d7ec351b56": {
    "status": "accepted",
    "updatedAt": "2026-07-02T02:52:58.687803Z",
    "auto": true
  },
  "rec_20260702_025256_666": {
    "status": "accepted",
    "updatedAt": "2026-07-02T02:52:58.687806Z",
    "auto": true
  },
  "rec_20260702_025256_579": {
    "status": "accepted",
    "updatedAt": "2026-07-02T02:52:58.687811Z",
    "auto": true
  },
  "rec_20260702_025256_879": {
    "status": "accepted",
    "updatedAt": "2026-07-02T02:52:58.687815Z",
    "auto": true
  },
  "rec_20260702_025256_590": {
    "status": "accepted",
    "updatedAt": "2026-07-02T02:52:58.687820Z",
    "auto": true
  },
  "rec_20260702_025256_295": {
    "status": "accepted",
    "updatedAt": "2026-07-02T02:52:58.687825Z",
    "auto": true
  },
  "rec_20260702_025256_498": {
    "status": "accepted",
    "updatedAt": "2026-07-02T02:52:58.687828Z",
    "auto": true
  },
  "rec_20260702_025308_992": {
    "status": "accepted",
    "updatedAt": "2026-07-02T02:53:10.135149Z",
    "auto": true
  },
  "rec_20260702_025308_406": {
    "status": "accepted",
    "updatedAt": "2026-07-02T02:53:10.135339Z",
    "auto": true
  },
  "rec_20260702_025308_295": {
    "status": "accepted",
    "updatedAt": "2026-07-02T02:53:10.135346Z",
    "auto": true
  },
  "rec_20260702_025308_174": {
    "status": "accepted",
    "updatedAt": "2026-07-02T02:53:10.135350Z",
    "auto": true
  },
  "rec_20260702_025308_603": {
    "status": "accepted",
    "updatedAt": "2026-07-02T02:53:10.135354Z",
    "auto": true
  },
  "rec_20260702_025308_831": {
    "status": "accepted",
    "updatedAt": "2026-07-02T02:53:10.135358Z",
    "auto": true
  },
  "rec_20260702_025308_339": {
    "status": "accepted",
    "updatedAt": "2026-07-02T02:53:10.135361Z",
    "auto": true
  },
  "rec_20260702_025308_617": {
    "status": "accepted",
    "updatedAt": "2026-07-02T02:53:10.135365Z",
    "auto": true
  },
  "rec_20260702_025322_303": {
    "status": "accepted",
    "updatedAt": "2026-07-02T02:53:23.387962Z",
    "auto": true
  },
  "rec_20260702_025322_675": {
    "status": "accepted",
    "updatedAt": "2026-07-02T02:53:23.388132Z",
    "auto": true
  },
  "rec_20260702_025322_835": {
    "status": "accepted",
    "updatedAt": "2026-07-02T02:53:23.388138Z",
    "auto": true
  },
  "rec_20260702_025322_176": {
    "status": "accepted",
    "updatedAt": "2026-07-02T02:53:23.388144Z",
    "auto": true
  },
  "rec_20260702_025322_337": {
    "status": "accepted",
    "updatedAt": "2026-07-02T02:53:23.388152Z",
    "auto": true
  },
  "rec_20260702_025338_151": {
    "status": "accepted",
    "updatedAt": "2026-07-02T02:53:39.873999Z",
    "auto": true
  },
  "rec_20260702_025338_912": {
    "status": "accepted",
    "updatedAt": "2026-07-02T02:53:39.874258Z",
    "auto": true
  },
  "rec_20260702_025338_177": {
    "status": "accepted",
    "updatedAt": "2026-07-02T02:53:39.874272Z",
    "auto": true
  },
  "rec_20260702_025338_509": {
    "status": "accepted",
    "updatedAt": "2026-07-02T02:53:39.874290Z",
    "auto": true
  },
  "rec_20260702_025338_222": {
    "status": "accepted",
    "updatedAt": "2026-07-02T02:53:39.874299Z",
    "auto": true
  },
  "ed01410c-8e55-4674-8011-5d2bfa74945f": {
    "status": "accepted",
    "updatedAt": "2026-07-02T02:59:01.140532Z",
    "auto": true
  },
  "c989ef7d-804d-45cf-bffd-1e67a542ab06": {
    "status": "accepted",
    "updatedAt": "2026-07-02T02:59:01.140639Z",
    "auto": true
  },
  "5d719f13-7304-4bea-92b1-560c04c1ce15": {
    "status": "accepted",
    "updatedAt": "2026-07-02T02:59:01.140645Z",
    "auto": true
  },
  "3df02809-2380-4cce-a1c0-2299adf83317": {
    "status": "accepted",
    "updatedAt": "2026-07-02T02:59:01.140648Z",
    "auto": true
  },
  "0fbfce56-a57c-4319-9f65-01962a4068e0": {
    "status": "accepted",
    "updatedAt": "2026-07-02T02:59:01.140652Z",
    "auto": true
  },
  "fd8c128b-c05a-4edd-a7ff-2477919a2b87": {
    "status": "accepted",
    "updatedAt": "2026-07-02T02:59:01.140655Z",
    "auto": true
  },
  "267630c0-524d-438e-8da5-7709fb3a32f1": {
    "status": "accepted",
    "updatedAt": "2026-07-02T02:59:01.140658Z",
    "auto": true
  },
  "191ea21e-413b-41f9-b909-61e7ea1be8c4": {
    "status": "accepted",
    "updatedAt": "2026-07-02T02:59:01.140661Z",
    "auto": true
  },
  "rec_20260702_025859_670": {
    "status": "accepted",
    "updatedAt": "2026-07-02T02:59:01.140665Z",
    "auto": true
  },
  "rec_20260702_025859_233": {
    "status": "accepted",
    "updatedAt": "2026-07-02T02:59:01.140671Z",
    "auto": true
  },
  "rec_20260702_025859_307": {
    "status": "accepted",
    "updatedAt": "2026-07-02T02:59:01.140677Z",
    "auto": true
  },
  "rec_20260702_025859_861": {
    "status": "accepted",
    "updatedAt": "2026-07-02T02:59:01.140682Z",
    "auto": true
  },
  "rec_20260702_025859_153": {
    "status": "accepted",
    "updatedAt": "2026-07-02T02:59:01.140686Z",
    "auto": true
  },
  "rec_20260702_025908_333": {
    "status": "accepted",
    "updatedAt": "2026-07-02T02:59:09.999280Z",
    "auto": true
  },
  "rec_20260702_025908_408": {
    "status": "accepted",
    "updatedAt": "2026-07-02T02:59:09.999423Z",
    "auto": true
  },
  "rec_20260702_025908_113": {
    "status": "accepted",
    "updatedAt": "2026-07-02T02:59:09.999431Z",
    "auto": true
  },
  "rec_20260702_025908_701": {
    "status": "accepted",
    "updatedAt": "2026-07-02T02:59:09.999436Z",
    "auto": true
  },
  "rec_20260702_025908_928": {
    "status": "accepted",
    "updatedAt": "2026-07-02T02:59:09.999442Z",
    "auto": true
  },
  "rec_20260702_025908_668": {
    "status": "accepted",
    "updatedAt": "2026-07-02T02:59:09.999446Z",
    "auto": true
  },
  "rec_20260702_025908_189": {
    "status": "accepted",
    "updatedAt": "2026-07-02T02:59:09.999449Z",
    "auto": true
  },
  "rec_20260702_025908_377": {
    "status": "accepted",
    "updatedAt": "2026-07-02T02:59:09.999452Z",
    "auto": true
  },
  "rec_20260702_025908_964": {
    "status": "accepted",
    "updatedAt": "2026-07-02T02:59:09.999456Z",
    "auto": true
  },
  "rec_20260702_025911_469": {
    "status": "accepted",
    "updatedAt": "2026-07-02T02:59:11.959001Z",
    "auto": true
  },
  "rec_20260702_025911_573": {
    "status": "accepted",
    "updatedAt": "2026-07-02T02:59:11.959167Z",
    "auto": true
  },
  "rec_20260702_025911_954": {
    "status": "accepted",
    "updatedAt": "2026-07-02T02:59:11.959172Z",
    "auto": true
  },
  "rec_20260702_025911_599": {
    "status": "accepted",
    "updatedAt": "2026-07-02T02:59:11.959177Z",
    "auto": true
  },
  "rec_20260702_025911_623": {
    "status": "accepted",
    "updatedAt": "2026-07-02T02:59:11.959181Z",
    "auto": true
  },
  "rec_20260702_025921_797": {
    "status": "accepted",
    "updatedAt": "2026-07-02T02:59:23.625327Z",
    "auto": true
  },
  "rec_20260702_025921_842": {
    "status": "accepted",
    "updatedAt": "2026-07-02T02:59:23.625468Z",
    "auto": true
  },
  "rec_20260702_025921_591": {
    "status": "accepted",
    "updatedAt": "2026-07-02T02:59:23.625476Z",
    "auto": true
  },
  "rec_20260702_025921_311": {
    "status": "accepted",
    "updatedAt": "2026-07-02T02:59:23.625483Z",
    "auto": true
  },
  "rec_20260702_025921_920": {
    "status": "accepted",
    "updatedAt": "2026-07-02T02:59:23.625487Z",
    "auto": true
  },
  "rec_20260702_025921_399": {
    "status": "accepted",
    "updatedAt": "2026-07-02T02:59:23.625491Z",
    "auto": true
  },
  "rec_20260702_025921_846": {
    "status": "accepted",
    "updatedAt": "2026-07-02T02:59:23.625494Z",
    "auto": true
  },
  "rec_20260702_025921_956": {
    "status": "accepted",
    "updatedAt": "2026-07-02T02:59:23.625498Z",
    "auto": true
  },
  "rec_20260702_025924_267": {
    "status": "accepted",
    "updatedAt": "2026-07-02T02:59:24.744653Z",
    "auto": true
  },
  "rec_20260702_025924_918": {
    "status": "accepted",
    "updatedAt": "2026-07-02T02:59:24.744789Z",
    "auto": true
  },
  "rec_20260702_025924_579": {
    "status": "accepted",
    "updatedAt": "2026-07-02T02:59:24.744795Z",
    "auto": true
  },
  "rec_20260702_025924_228": {
    "status": "accepted",
    "updatedAt": "2026-07-02T02:59:24.744799Z",
    "auto": true
  },
  "rec_20260702_025924_548": {
    "status": "accepted",
    "updatedAt": "2026-07-02T02:59:24.744808Z",
    "auto": true
  },
  "rec_20260702_025924_146": {
    "status": "accepted",
    "updatedAt": "2026-07-02T02:59:24.744814Z",
    "auto": true
  },
  "rec_20260702_025924_853": {
    "status": "accepted",
    "updatedAt": "2026-07-02T02:59:24.744817Z",
    "auto": true
  },
  "rec_20260702_025932_682": {
    "status": "accepted",
    "updatedAt": "2026-07-02T02:59:33.726788Z",
    "auto": true
  },
  "rec_20260702_025932_503": {
    "status": "accepted",
    "updatedAt": "2026-07-02T02:59:33.726914Z",
    "auto": true
  },
  "rec_20260702_025932_500": {
    "status": "accepted",
    "updatedAt": "2026-07-02T02:59:33.726921Z",
    "auto": true
  },
  "rec_20260702_025932_516": {
    "status": "accepted",
    "updatedAt": "2026-07-02T02:59:33.726925Z",
    "auto": true
  },
  "rec_20260702_025932_575": {
    "status": "accepted",
    "updatedAt": "2026-07-02T02:59:33.726929Z",
    "auto": true
  },
  "rec_20260702_025932_661": {
    "status": "accepted",
    "updatedAt": "2026-07-02T02:59:33.726932Z",
    "auto": true
  },
  "rec_20260702_025932_834": {
    "status": "accepted",
    "updatedAt": "2026-07-02T02:59:33.726936Z",
    "auto": true
  },
  "rec_20260702_025932_298": {
    "status": "accepted",
    "updatedAt": "2026-07-02T02:59:33.726939Z",
    "auto": true
  },
  "rec_20260702_025932_337": {
    "status": "accepted",
    "updatedAt": "2026-07-02T02:59:33.726943Z",
    "auto": true
  },
  "rec_20260702_025933_947": {
    "status": "accepted",
    "updatedAt": "2026-07-02T02:59:33.726946Z",
    "auto": true
  },
  "rec_20260702_025933_994": {
    "status": "accepted",
    "updatedAt": "2026-07-02T02:59:33.726949Z",
    "auto": true
  },
  "rec_20260702_025933_631": {
    "status": "accepted",
    "updatedAt": "2026-07-02T02:59:33.726955Z",
    "auto": true
  },
  "rec_20260702_025933_735": {
    "status": "accepted",
    "updatedAt": "2026-07-02T02:59:33.726958Z",
    "auto": true
  },
  "rec_20260702_025933_526": {
    "status": "accepted",
    "updatedAt": "2026-07-02T02:59:33.726963Z",
    "auto": true
  },
  "rec_20260702_025933_473": {
    "status": "accepted",
    "updatedAt": "2026-07-02T02:59:33.726968Z",
    "auto": true
  },
  "rec_20260702_025933_448": {
    "status": "accepted",
    "updatedAt": "2026-07-02T03:07:53.349Z"
  },
  "1abf6631-b2e8-4ba2-8763-e6cc7e9b56fe": {
    "status": "accepted",
    "updatedAt": "2026-07-02T03:08:00.044Z"
  },
  "rec_20260702_025933_130": {
    "status": "rejected",
    "updatedAt": "2026-07-02T03:08:06.080Z"
  },
  "rec_20260702_025921_827": {
    "status": "accepted",
    "updatedAt": "2026-07-02T03:08:14.545Z"
  },
  "4854ac1b-7f53-4ad0-a288-80c7be318166": {
    "status": "accepted",
    "updatedAt": "2026-07-02T03:20:37.787Z"
  },
  "rec_20260702_025924_664": {
    "status": "accepted",
    "updatedAt": "2026-07-02T03:20:48.808Z"
  }
}